{
  "name": "Custom Theme",
  "dataColors": [
    "#83d4d9",
    "#b03372",
    "#5d37b0",
    "#dfbd36",
    "#8a3535"
  ],
  "foreground": "#f9fafb",
  "background": "#1e293b",
  "foregroundNeutralSecondary": "#d1d5db",
  "backgroundLight": "#0f172a",
  "foregroundNeutralTertiary": "#d1d5db",
  "backgroundNeutral": "#334155",
  "tableAccent": "#83d4d9",
  "maximum": "#5d37b0",
  "center": "#b03372",
  "minimum": "#83d4d9",
  "bad": "#83d4d9",
  "neutral": "#b03372",
  "good": "#5d37b0",
  "textClasses": {
    "callout": {
      "color": "#f9fafb",
      "fontFace": "'Segoe UI', Tahoma, Geneva, Verdana, sans-serif"
    },
    "title": {
      "color": "#f9fafb",
      "fontFace": "'Segoe UI', Tahoma, Geneva, Verdana, sans-serif"
    },
    "header": {
      "color": "#f9fafb",
      "fontFace": "'Segoe UI', Tahoma, Geneva, Verdana, sans-serif"
    },
    "label": {
      "color": "#f9fafb",
      "fontFace": "'Segoe UI', Tahoma, Geneva, Verdana, sans-serif"
    }
  },
  "visualStyles": {
    "*": {
      "*": {
        "background": [
          {
            "color": {
              "solid": {
                "color": "#334155"
              }
            }
          }
        ],
        "border": [
          {
            "color": {
              "solid": {
                "color": "#334155"
              }
            },
            "show": true,
            "radius": 8
          }
        ],
        "visualHeader": [
          {
            "background": {
              "solid": {
                "color": "#334155"
              }
            },
            "border": {
              "solid": {
                "color": "#334155"
              }
            }
          }
        ]
      }
    },
    "page": {
      "*": {
        "outspace": [
          {
            "color": {
              "solid": {
                "color": "#0f172a"
              }
            }
          }
        ],
        "outspacePane": [
          {
            "backgroundColor": {
              "solid": {
                "color": "#ffffff"
              }
            },
            "foregroundColor": {
              "solid": {
                "color": "#000000"
              }
            }
          }
        ],
        "background": [
          {
            "color": {
              "solid": {
                "color": "#1e293b"
              }
            },
            "transparency": 0
          }
        ],
        "filterCard": [
          {
            "$id": "Applied",
            "backgroundColor": {
              "solid": {
                "color": "#ececec"
              }
            },
            "foregroundColor": {
              "solid": {
                "color": "#000000"
              }
            },
            "transparency": 0
          },
          {
            "$id": "Available",
            "backgroundColor": {
              "solid": {
                "color": "#ffffff"
              }
            },
            "foregroundColor": {
              "solid": {
                "color": "#000000"
              }
            },
            "transparency": 0
          }
        ]
      }
    }
  }
}